pywayne/__init__.py
pywayne/__version__.py
pywayne/aliyun_oss.py
pywayne/cross_comm.py
pywayne/crypto.py
pywayne/data_structure.py
pywayne/dsp.py
pywayne/gui.py
pywayne/helper.py
pywayne/lark_bot.py
pywayne/lark_bot_listener.py
pywayne/lark_custom_bot.py
pywayne/maths.py
pywayne/plot.py
pywayne/tools.py
pywayne/tts.py
pywayne/adb/__init__.py
pywayne/adb/logcat_reader.py
pywayne/ahrs/__init__.py
pywayne/ahrs/tools.py
pywayne/calibration/__init__.py
pywayne/calibration/magnetometer_calibration.py
pywayne/calibration/temporal_calibration.py
pywayne/cv/__init__.py
pywayne/cv/apriltag_detector.py
pywayne/cv/camera_model.py
pywayne/cv/geometric_hull_calculator.py
pywayne/cv/stereo_tag_matcher.py
pywayne/cv/tools.py
pywayne/llm/__init__.py
pywayne/llm/chat_bot.py
pywayne/llm/chat_ollama_gradio.py
pywayne/llm/chat_window.py
pywayne/statistics/__init__.py
pywayne/statistics/base.py
pywayne/statistics/correlation_tests.py
pywayne/statistics/examples.py
pywayne/statistics/location_tests.py
pywayne/statistics/model_diagnostics.py
pywayne/statistics/normality_tests.py
pywayne/statistics/time_series_tests.py
pywayne/statistics/utils.py
pywayne/vio/SE3.py
pywayne/vio/SO3.py
pywayne/vio/__init__.py
pywayne/vio/tools.py
pywayne/visualization/__init__.py
pywayne/visualization/pangolin_utils.py
pywayne/visualization/rerun_utils.py
pywayne-1.0.1.5.6.data/scripts/cmdlogger
pywayne-1.0.1.5.6.data/scripts/cmdlogger.py
pywayne-1.0.1.5.6.data/scripts/gettool
pywayne-1.0.1.5.6.data/scripts/gettool.py
pywayne-1.0.1.5.6.data/scripts/gitstats
pywayne-1.0.1.5.6.data/scripts/gitstats.py
pywayne-1.0.1.5.6.dist-info/licenses/LICENSE
pywayne-1.0.1.5.6.dist-info/METADATA
pywayne-1.0.1.5.6.dist-info/WHEEL
pywayne-1.0.1.5.6.dist-info/dependency_links.txt
pywayne-1.0.1.5.6.dist-info/top_level.txt
pywayne-1.0.1.5.6.dist-info/RECORD
